sercol/__init__.py
sercol/collection.py
sercol-1.0.0.dist-info/LICENSE
sercol-1.0.0.dist-info/METADATA
sercol-1.0.0.dist-info/WHEEL
sercol-1.0.0.dist-info/top_level.txt
sercol-1.0.0.dist-info/RECORD
