Metadata-Version: 2.1
Name: sercol
Version: 1.0.0
Summary: Rich collection class with grouping and filtering helpers
Home-page: https://github.com/openvax/sercol
Author: Alex Rubinsteyn
Author-email: alex.rubinsteyn@unc.edu
License: http://www.apache.org/licenses/LICENSE-2.0.html
Classifier: Development Status :: 4 - Beta
Classifier: Environment :: Console
Classifier: Operating System :: OS Independent
Classifier: License :: OSI Approved :: Apache Software License
Classifier: Programming Language :: Python
License-File: LICENSE
Requires-Dist: simplejson
Requires-Dist: serializable
Requires-Dist: pandas
